{
  "unversionedId": "how-to/custom-color-profile",
  "id": "how-to/custom-color-profile",
  "title": "Customize the color scheme",
  "description": "You can make changes to the colors of the website to make it unique and more personalized.",
  "source": "@site/docs/how-to/custom-color-profile.md",
  "sourceDirName": "how-to",
  "slug": "/how-to/custom-color-profile",
  "permalink": "/docs/how-to/custom-color-profile",
  "draft": false,
  "editUrl": "https://github.com/morethanthemes/docs/edit/master/docs/how-to/custom-color-profile.md",
  "tags": [],
  "version": "current",
  "sidebarPosition": 2,
  "frontMatter": {
    "sidebar_position": 2
  },
  "sidebar": "tutorialSidebar",
  "previous": {
    "title": "Customize the theme",
    "permalink": "/docs/how-to/customize-theme"
  },
  "next": {
    "title": "Host Google fonts locally",
    "permalink": "/docs/how-to/google-fonts-locally"
  }
}